LICENSE
README.md
setup.py
repcalchn/DecimalTime.py
repcalchn/RepublicanDate.py
repcalchn/RepublicanFormatter.py
repcalchn/__init__.py
repcalchn/__main__.py
repcalchn/chinese_name.py
repcalchn/command_line.py
repcalchn.egg-info/PKG-INFO
repcalchn.egg-info/SOURCES.txt
repcalchn.egg-info/dependency_links.txt
repcalchn.egg-info/entry_points.txt
repcalchn.egg-info/top_level.txt