Metadata-Version: 2.1
Name: repcalchn
Version: 1.0.0
Summary: The French Republican calendar and decimal time in Python in Chinese and French
Home-page: https://github.com/git-thinker/repcalchn
Author: Doctor
Author-email: 
License: MIT
Classifier: Programming Language :: Python :: 3
Classifier: License :: OSI Approved :: MIT License
Classifier: Operating System :: OS Independent
Requires-Python: >=3.6
License-File: LICENSE
